workers_kv/__init__.py
workers_kv/ext/async_workers_kv/__init__.py
workers_kv/ext/async_workers_kv/aio_request.py
workers_kv.py-1.2.2.dist-info/METADATA
workers_kv.py-1.2.2.dist-info/WHEEL
workers_kv.py-1.2.2.dist-info/top_level.txt
workers_kv.py-1.2.2.dist-info/RECORD
