Metadata-Version: 2.1
Name: workers-kv.py
Version: 1.2.2
Summary: An api wrapper of Cloudflare Workers KV for Python
Home-page: https://github.com/Alpaca131/workers-kv-py
Author: Alpaca131
Author-email: contact@alpaca131.com
License: MIT
Platform: UNKNOWN
Classifier: Programming Language :: Python :: 3
Classifier: License :: OSI Approved :: MIT License
Classifier: Operating System :: OS Independent
Requires-Python: >=3.8
Requires-Dist: requests (>=2.25.1)
Requires-Dist: aiohttp (>=3.8.1)
